README.txt
setup.py
vaquita/__init__.py
vaquita/iv.py
vaquita.egg-info/PKG-INFO
vaquita.egg-info/SOURCES.txt
vaquita.egg-info/dependency_links.txt
vaquita.egg-info/top_level.txt
vaquita.egg-info/zip-safe