Metadata-Version: 1.1
Name: vaquita
Version: 0.12
Summary: this is a test package for packing python liberaries tutorial.
Home-page: http://github.com/lihuapeng
Author: lihuapeng
Author-email: lihuapeng@live.com
License: MIT
Keywords: vaquita python package
Platform: UNKNOWN
Classifier: License :: OSI Approved :: MIT License
Classifier: Programming Language :: Python
Classifier: Intended Audience :: Developers
Classifier: Operating System :: OS Independent
